README.txt
setup.cfg
setup.py
docs/HISTORY.txt
docs/INSTALL.txt
docs/LICENSE.txt
hexagonit/__init__.py
hexagonit.form.egg-info/PKG-INFO
hexagonit.form.egg-info/SOURCES.txt
hexagonit.form.egg-info/dependency_links.txt
hexagonit.form.egg-info/entry_points.txt
hexagonit.form.egg-info/namespace_packages.txt
hexagonit.form.egg-info/not-zip-safe
hexagonit.form.egg-info/paster_plugins.txt
hexagonit.form.egg-info/top_level.txt
hexagonit/form/__init__.py
hexagonit/form/interfaces.py
hexagonit/form/orderable.py
hexagonit/form/orderable.txt
hexagonit/form/tests.py
