Metadata-Version: 1.0
Name: hexagonit.form
Version: 0.1
Summary: Orderable variant of zope.formlib.form.Fields.
Home-page: UNKNOWN
Author: Kai Lautaportti
Author-email: kai.lautaportti@hexagonit.fi
License: ZPL
Keywords: formlib fields ordering
Platform: UNKNOWN
Classifier: Framework :: Zope2
Classifier: Framework :: Zope3
Classifier: Programming Language :: Python
Classifier: Topic :: Software Development :: Libraries :: Python Modules
Classifier: License :: OSI Approved :: Zope Public License
